<?xml version="1.0" encoding="utf-8"?>
<Database xmlns:xsd="http://www.w3.org/2001/XMLSchema" xmlns:xsi="http://www.w3.org/2001/XMLSchema-instance" Name="brambora">
	<Skald>
		<Module Name="teleportfromareainpatchphase">
			<Ports>
				<AssetPort Name="soul" Direction="In" Type="wh::rpgmodule::I_Soul*" Alias="player_any">
					<DesignName StringName="teleportf_soul_Q7io" Text="Soul" />
				</AssetPort>
				<Port Name="transitiontoversion" Direction="In" Type="wh::framework::E_GameReleaseVersion">
					<DesignName StringName="teleportf_transitiontover_VNZo" Text="TransitionToVersion" />
				</Port>
				<Port Name="area" Direction="In" Type="wh::xgenaimodule::Areas">
					<DesignName StringName="teleportf_area_EjvL" Text="Area" />
				</Port>
				<Port Name="destination" Direction="In" Type="wh::xgenaimodule::LinkableObject*">
					<DesignName StringName="teleportf_destination_hGEH" Text="Destination" />
				</Port>
			</Ports>
			<Nodes>
				<AddInterruptConceptNode Name="addInterruptTeleport" PositionY="-60" PositionX="540" Signature="teleport">
					<Constant Name="Behavior" Value="teleport" />
					<Asset Name="SmartEntity" Alias="land" />
					<Constant Name="Priority" Value="255" />
					<Constant Name="Urgency" Value="Instant" />
					<Edge From="soul" To="NPC">
						<Vertex>GJCokM4q</Vertex>
						<Vertex>SdqWG6ad</Vertex>
					</Edge>
					<Edge From="destination" To="destination">
						<Vertex>U37cjkjL</Vertex>
					</Edge>
					<Edge From="ifSoulInArea.True" To="Activate" />
				</AddInterruptConceptNode>
				<IfFunction Name="ifSoulInArea" PositionY="-60" PositionX="270" MethodName="wh::rpgmodule::AreaCheck" DeclaringType="wh::rpgmodule">
					<Edge From="area" To="Areas">
						<Vertex>C8tVDhsT</Vertex>
					</Edge>
					<Edge From="patchtrigger.OnPatch" To="Exec" />
					<Edge From="makeSoulArray.Array" To="Souls" />
				</IfFunction>
				<MakeArray Name="makeSoulArray" PositionY="140" PositionX="-10" TypeT="wh::rpgmodule::Souls">
					<Edge From="soul" To="A">
						<Vertex>GJCokM4q</Vertex>
					</Edge>
				</MakeArray>
				<PatchTrigger Name="patchtrigger" PositionY="-60" PositionX="-160">
					<Edge From="transitiontoversion" To="TransitionToVersion" />
				</PatchTrigger>
			</Nodes>
			<EdgeVertices>
				<EdgeVertex Name="C8tVDhsT" PositionY="90" PositionX="-150" />
				<EdgeVertex Name="GJCokM4q" PositionY="130" PositionX="-150" />
				<EdgeVertex Name="SdqWG6ad" PositionY="130" PositionX="460" />
				<EdgeVertex Name="U37cjkjL" PositionY="280" PositionX="-160" />
			</EdgeVertices>
			<Text StringName="teleportfromareainpatchph_rRi0" Text="TeleportFromAreaInPatchPhase" />
		</Module>
	</Skald>
</Database>