<?xml version="1.0" encoding="utf-8"?>
<Database xmlns:xsd="http://www.w3.org/2001/XMLSchema" xmlns:xsi="http://www.w3.org/2001/XMLSchema-instance" Name="brambora">
	<Skald>
		<FaderDialog Name="magdalena_hintuje_aktivitu">
			<Ports>
				<Port Name="aktivita_je_dostupna" Direction="In" Type="bool">
					<DesignName StringName="magdalena_aktivita_je_dos_SPcH" Text="Aktivita je dostupná" />
				</Port>
			</Ports>
			<Text StringName="magdalena_hintuje_aktivitu_NVVj" Text="Magdaléna hintuje aktivitu" />
			<Elements>
				<GameplayActionElement>
					<Text StringName="magdalena_magdalena_hintu_hsQr" Text="Magdaléna hintuje aktivitu s velitelem stráží." />
				</GameplayActionElement>
			</Elements>
			<Dialogue TechnicalStatus="Enabled" GesturesSetDate="2025-10-28T19:04:07.8487097+01:00" GesturesSetResponseCount="3">
				<SelectedSouls>
					<SelectedSoul Role="HENRY" Voice="tomMcKay" Type="Wave" Language="ENG" />
					<SelectedSoul Role="MAGDALENA" Voice="andreaMiltnerova" Type="Wave" Language="ENG" />
				</SelectedSouls>
				<Decision Name="dec1" Priority="SideQuestAssignment">
					<Sequences>
						<Sequence EntryCondition="Port('aktivita_je_dostupna') AND&#xD;&#xA;!ThisSequenceUsed() " Visibility="Public" Type="DLC2_smithing" Name="magdalena_tipnula_aktivitu">
							<DesignName StringName="magdalena_seq1_pXGo" Text="Magdaléna tipnula aktivitu" />
							<UiPrompt StringName="ui_magdalena_seq1_KpUs" Text="Co je nového?" />
							<Elements>
								<Response Role="HENRY" ReferenceLength="0.84">
									<Parenthetical>
										<Text StringName="magd_henry_vecne_mCbo" Text="věcně" />
									</Parenthetical>
									<Text StringName="magd_henry_mas_pro_me_nej_e181" Text="Co je novýho?" />
									<Commands>
										<FacialMoodCommand FacialMood="thinking1" />
										<FacialMoodCommand Role="MAGDALENA" FacialMood="thinking1" />
										<AnimationCommand Delay="0" FragmentId="ADLG_Gesture" Guid="f15da38f-1fd7-45d6-9587-0b74338f13fc" Variant="24" />
										<CameraCommand CameraType="CloseUp" />
									</Commands>
								</Response>
								<Response Role="MAGDALENA" ReferenceLength="5.75">
									<Parenthetical>
										<Text StringName="magd_magdalena_suse_UBVj" Text="suše" />
									</Parenthetical>
									<Text StringName="magd_magdalena_ja_ne_ale__Efk3" Text="Stavil se tady jeden kluk vod stráže, že by s tebou chtěl mluvit jejich velitel, mladej Plümel." />
									<Commands>
										<AnimationCommand Delay="2.32" FragmentId="ADLG_Gesture" Guid="447b018f-9485-446f-a811-c0cde0b017f7" Variant="4" />
										<CameraCommand CameraType="CloseShot" />
									</Commands>
								</Response>
								<Response Role="MAGDALENA" ReferenceLength="6.93">
									<Parenthetical>
										<Text StringName="magd_magdalena_uznale_NnDe" Text="uznale" />
									</Parenthetical>
									<Text StringName="magd_magdalena_zajdi_za_n_uqMz" Text="Zajdi za ním a přeptej se co potřebuje. Taková práce pro město, to by bylo něco. Z toho už koukaj hezký peníze! " />
									<Commands>
										<FacialMoodCommand FacialMood="thinking2" />
										<AnimationCommand Delay="0.08" FragmentId="ADLG_Agree" Guid="3855e936-aaa8-40bb-a9c6-c4a26f4a19e5" Variant="0" />
										<AnimationCommand Delay="5.19" FragmentId="ADLG_Emphasis" Guid="997de6b9-12de-4de4-886f-820e118601d6" Variant="5" />
									</Commands>
								</Response>
							</Elements>
						</Sequence>
					</Sequences>
				</Decision>
			</Dialogue>
		</FaderDialog>
	</Skald>
</Database>