<?xml version="1.0" encoding="us-ascii"?>
<database name="barbora" xmlns:xsi="http://www.w3.org/2001/XMLSchema-instance" xsi:noNamespaceSchemaLocation="../../database.xsd">
	<SmartEntitys version="1">
		<SmartEntityTemplate DatabaseId="e99c0277-c0cf-4ef8-a6eb-426a6782ee96" Name="so_animalBehaviors_deer" UpdatePriority="false">
			<BehaviorTemplates>
				<SmartBehaviorTemplate InitialState="Enabled" MaxInstances="-1" Name="use_eat">
					<TreeLocation FileName="animal/so_animalBehaviors_deer.xml" TreeName="use_eat" />
				</SmartBehaviorTemplate>
				<SmartBehaviorTemplate InitialState="Enabled" MaxInstances="-1" Name="use_moo">
					<TreeLocation FileName="animal/so_animalBehaviors_deer.xml" TreeName="use_moo" />
				</SmartBehaviorTemplate>
				<SmartBehaviorTemplate InitialState="Enabled" MaxInstances="-1" Name="use_idle">
					<TreeLocation FileName="animal/so_animalBehaviors_deer.xml" TreeName="use_idle" />
				</SmartBehaviorTemplate>
				<SmartBehaviorTemplate InitialState="Enabled" MaxInstances="-1" Name="use_sleep">
					<TreeLocation FileName="animal/so_animalBehaviors_deer.xml" TreeName="use_sleep" />
				</SmartBehaviorTemplate>
			</BehaviorTemplates>
		</SmartEntityTemplate>
	</SmartEntitys>
</database>