<?xml version="1.0" encoding="utf-8"?>
<Database xmlns:xsd="http://www.w3.org/2001/XMLSchema" xmlns:xsi="http://www.w3.org/2001/XMLSchema-instance" Name="brambora">
	<Skald>
		<Module Name="stream_lebky_a_dzban_na_lavicce" Purpose="LocationControl">
			<Ports>
				<Port Name="nastreamovat" Direction="In" Type="trigger">
					<DesignName StringName="stream_le_nastreamovat_bLbK" Text="Nastreamovat" />
				</Port>
				<Port Name="odstreamovat" Direction="In" Type="trigger">
					<DesignName StringName="stream_le_odstreamovat_wkyx" Text="Odstreamovat" />
				</Port>
			</Ports>
			<Nodes>
				<Layer Name="profileSkullAndMeadProfile" PositionY="-20" PositionX="310">
					<Asset Name="Profiles" Alias="SkullAndMeadProfile" />
					<Edge From="stateSkullAndMeadProfile.Active" To="IsActive" />
				</Layer>
				<State Name="stateSkullAndMeadProfile" PositionY="-190" PositionX="0" TypeT="Progress">
					<Edge From="nastreamovat" To="SetActive" />
					<Edge From="odstreamovat" To="SetDone" />
				</State>
			</Nodes>
			<Assets>
				<ProfileAsset Name="SkullAndMeadProfile" AssetProfiles="truhlari_meadOnBench truhlari_skullOnBench" />
			</Assets>
			<Text StringName="stream_lebky_a_dzban_na_l_pH48" Text="Stream lebky a džbán na lavičce" />
		</Module>
	</Skald>
</Database>