<?xml version="1.0" encoding="utf-8"?>
<Database xmlns:xsd="http://www.w3.org/2001/XMLSchema" xmlns:xsi="http://www.w3.org/2001/XMLSchema-instance" Name="brambora">
	<Skald>
		<Gameplay Name="stavy_hrace_unavahlad" VoiceNamespace="true">
			<Ports>
				<Port Name="m03_socky" Direction="In" Type="wh::questmodule::QuestProgress">
					<DesignName StringName="stavy_hra_m03_socky_dfmk" Text="M03 Socky" />
				</Port>
			</Ports>
			<Definitions>
				<Definition File="stavy_hrace_unavahlad/hlad.xml" />
				<Definition File="stavy_hrace_unavahlad/unava.xml" />
				<Definition File="stavy_hrace_unavahlad/narazeni_na_barieru_voda_level.xml" />
				<Definition File="stavy_hrace_unavahlad/jedeni_z_kotliku.xml" />
				<Definition File="stavy_hrace_unavahlad/akohol_a_opilost.xml" />
				<Definition File="stavy_hrace_unavahlad/bezvedomi.xml" />
			</Definitions>
			<Nodes>
				<akohol_a_opilost Name="akohol_a_opilost" PositionY="410" PositionX="-140" />
				<bezvedomi Name="bezvedomi" PositionY="570" PositionX="-140" />
				<hlad Name="hlad" PositionY="70" PositionX="-140" />
				<jedeni_z_kotliku Name="jedeni_z_kotliku" PositionY="180" PositionX="-140" />
				<narazeni_na_barieru_voda_level Name="narazeni_na_barieru_voda_level" PositionY="10" PositionX="360">
					<Edge From="m03_socky" To="m03_socky" />
				</narazeni_na_barieru_voda_level>
				<unava Name="unava_1" PositionY="70" PositionX="80" />
			</Nodes>
			<Text StringName="stavy_hrace_unavahlad_oATB" Text="Stavy hráče (únava/hlad...)" />
		</Gameplay>
	</Skald>
</Database>