<?xml version="1.0" encoding="utf-8"?>
<Database xmlns:xsd="http://www.w3.org/2001/XMLSchema" xmlns:xsi="http://www.w3.org/2001/XMLSchema-instance" Name="brambora">
	<Skald>
		<Dialog Name="bark_k_prvni_casti_malby__cesta">
			<Text StringName="bark_k_prvni_casti_malby__ynnl" Text="Bark k první části malby - moře" />
			<Dialogue Type="ingame monolog" TechnicalStatus="Enabled" Initiator="NonPlayer" ClashPriority="Flavor" GesturesNotNeeded="true">
				<Decision Name="dec1" Alias="artefakt_barkKPrvniCastiMalbyCesta">
					<Sequences>
						<Sequence EndType="EndDialogue" Name="seq1">
							<DesignName StringName="bark_k_pr_seq1_w6dz" Text="seq1" />
							<Elements>
								<Response Role="HENRY">
									<Parenthetical>
										<Text StringName="bark_henry_kouka_na_malbu_Brfg" Text="kouká na malbu a interpretuje si to" />
									</Parenthetical>
									<Text StringName="bark_henry_p_tohle_budou__LATy" Text="Začátek Bavorovy cesty. To budou asi Benátky a Jeruzalém." />
								</Response>
							</Elements>
						</Sequence>
					</Sequences>
				</Decision>
			</Dialogue>
		</Dialog>
	</Skald>
</Database>