<?xml version="1.0" encoding="utf-8"?>
<Database xmlns:xsd="http://www.w3.org/2001/XMLSchema" xmlns:xsi="http://www.w3.org/2001/XMLSchema-instance" Name="brambora">
	<Skald>
		<ActivityType Name="A201_kovani" HibernateMode="ActivityType" VoiceNamespace="true" HasteNamespace="true">
			<Ports>
				<Port Name="debug_aktivovan" Direction="In" Type="bool">
					<DesignName StringName="a201_kova_debug_aktivovan_MEkJ" Text="debug frameworku aktivovan" />
				</Port>
				<Port Name="nastreamovat_truhlu_ve_zbrojnici" Direction="Out" Type="trigger">
					<DesignName StringName="a201_kova_nastreamovat_tr_EJTs" Text="Zbrojince - Nastreamovat truhlu" />
				</Port>
				<Port Name="jindra_se_dozvida_o_klici_ve_meste" Direction="Out" Type="trigger">
					<DesignName StringName="a201_kova_jindra_se_dozvi_OnTH" Text="Zbrojnice - Jindra se dozvídá o klíči ve městě" />
				</Port>
				<Port Name="zbrojnice__jindra_sebral_klic" Direction="Out" Type="trigger">
					<DesignName StringName="a201_kova_zbrojnice__jind_50DH" Text="Zbrojnice - Jindra sebral klíč" />
				</Port>
				<Port Name="jindra_predal_klic_strazi" Direction="Out" Type="trigger">
					<DesignName StringName="a201_kova_jindra_predal_k_EsbU" Text="Zbrojnice - Jindra předal klíč stráži" />
				</Port>
				<Port Name="konci_quest" Direction="Out" Type="trigger">
					<DesignName StringName="a201_kova_konci_quest_F8Wy" Text="Zbrojnice - Končí quest" />
				</Port>
				<Port Name="horst_dava_jindrovi_zlomeny_excalibur" Direction="Out" Type="trigger">
					<DesignName StringName="a201_kova_horst_dava_jind_p1dN" Text="Horst dává Jindrovi zlomený Excalibur" />
				</Port>
				<Port Name="jindra_kove_excalibur" Direction="Out" Type="trigger">
					<DesignName StringName="a201_kova_jindra_kove_exc_nQAR" Text="Jindra kove Excalibur" />
				</Port>
				<Port Name="horst_dava_jindrovi_zlomeny_durendal" Direction="Out" Type="trigger">
					<DesignName StringName="a201_kova_horst_dava_jind_6TTz" Text="Horst dává Jindrovi zlomený Durendal" />
				</Port>
				<Port Name="jindra_kove_durendal" Direction="Out" Type="trigger">
					<DesignName StringName="a201_kova_jindra_kove_dur_URXm" Text="Jindra kove Durendal" />
				</Port>
				<Port Name="horst_dava_jindrovi_zlomeny_mec_4_evangelistu" Direction="Out" Type="trigger">
					<DesignName StringName="a201_kova_horst_dava_jind_u4aQ" Text="Horst dává Jindrovi zlomený meč 4 evangelistů" />
				</Port>
				<Port Name="jindra_kove_4_evangelisty" Direction="Out" Type="trigger">
					<DesignName StringName="a201_kova_jindra_kove_4_e_HTob" Text="Jindra kove 4 evangelisty" />
				</Port>
				<Port Name="fail_aktivity_prodejce_receptu" Direction="Out" Type="trigger">
					<DesignName StringName="a201_kova_fail_aktivity_p_qgxZ" Text="Fail aktivity prodejce receptů" />
				</Port>
				<Port Name="jindra_ma_za_ukol_vykovat_draci_sekeru" Direction="Out" Type="bool">
					<DesignName StringName="a201_kova_jindra_ma_za_uk_P5rr" Text="Prodejce receptů - Jindra má za úkol vykovat dračí sekeru" />
				</Port>
				<Port Name="prodejce_receptu__nastreamovat" Direction="Out" Type="trigger">
					<DesignName StringName="a201_kova_prodejce_recept_aIkA" Text="Prodejce receptů - Nastreamovat" />
				</Port>
				<Port Name="prodejce_receptu__odejit_z_levelu" Direction="Out" Type="trigger">
					<DesignName StringName="a201_kova_prodejce_recept_LB8T" Text="Prodejce receptů - Odejít z levelu" />
				</Port>
				<Port Name="jindra_trhal_zub_v_poi_na_kovarne" Direction="In" Type="bool">
					<DesignName StringName="a201_kova_jindra_trhal_zub_709q" Text="Jindra trhal zub v POI Na Kovárně" />
				</Port>
				<Port Name="prodejce_receptu_1__quest_progress_none" Direction="Out" Type="bool">
					<DesignName StringName="a201_kova_quest_progress__nWVv" Text="Prodejce receptů 1 - Quest progress none" />
				</Port>
				<Port Name="zubar__quest_progress_none" Direction="Out" Type="bool">
					<DesignName StringName="a201_kova_quest_progress__jb33" Text="Zubař - Quest progress none" />
				</Port>
				<Port Name="zubar__first_objective_none" Direction="Out" Type="bool">
					<DesignName StringName="a201_kova_zubar__first_ob_eS3o" Text="Zubař - First objective none" />
				</Port>
				<Port Name="zubar__nastavit_pacientovi_zakrvacenou_hlavu" Direction="Out" Type="trigger">
					<DesignName StringName="a201_kova_zubar__nastavit_llUL" Text="Zubař - Nastavit pacientovi zakrvácenou hlavu" />
				</Port>
				<Port Name="zubar__pacient_svevolne_pada_do_bezvedomi" Direction="Out" Type="trigger">
					<DesignName StringName="a201_kova_zubar__pacient__gA0o" Text="Zubař - Pacient svévolně padá do bezvědomí" />
				</Port>
				<Port Name="aktivita_zacala" Direction="Out" Type="bool">
					<DesignName StringName="a201_kova_aktivita_zacala_JzYk" Text="Učedník - Aktivita začala" />
				</Port>
				<Port Name="jindra_vi_o_drakovi" Direction="In" Type="bool">
					<DesignName StringName="a201_kova_jindra_vi_o_dra_etLu" Text="S30 - Drak - Jindra ví o drakovi" />
				</Port>
				<Port Name="drak_state" Direction="In" Type="wh::questmodule::QuestProgress">
					<DesignName StringName="a201_kova_drak_state_2F4H" Text="S30 - Drak" />
				</Port>
				<Port Name="jindra_ziskal_fejxcalibur" Direction="In" Type="bool">
					<DesignName StringName="a201_kova_jindra_ziskal_f_kipc" Text="Jindra získal fejxcalibur" />
				</Port>
				<Port Name="jindra_ziskal_durensral" Direction="In" Type="bool">
					<DesignName StringName="a201_kova_jindra_ziskal_d_GTwL" Text="Jindra získal durensral" />
				</Port>
				<Port Name="jindra_ziskal_mec_4_evangelistu" Direction="In" Type="bool">
					<DesignName StringName="a201_kova_jindra_ziskal_m_LC96" Text="Jindra získal meč 4 evangelistů" />
				</Port>
				<Port Name="jindra_ziskal_draci_zbran" Direction="In" Type="bool">
					<DesignName StringName="a201_kova_jindra_ziskal_d_bvl3" Text="Jindra získal dračí zbraň" />
				</Port>
			</Ports>
			<Definitions>
				<Definition File="A201_kovani/kovaci_zakazka.xml" />
				<Definition File="A201_kovani/zubar.xml" />
				<Definition File="A201_kovani/vybirani_typu_aktivity.xml" />
				<Definition File="A201_kovani/zbrojnice.xml" />
				<Definition File="A201_kovani/prodejce_receptu.xml" />
				<Definition File="A201_kovani/ucednik.xml" />
			</Definitions>
			<Nodes>
				<HasteTrigger Name="01_initBlacksmithing" PositionY="-1180" PositionX="-1180">
					<Edge From="makearray26.Array" To="Prerequisites" />
				</HasteTrigger>
				<HasteTrigger Name="80_giveMaterialsAndRecipes" PositionY="-1440" PositionX="-20">
					<Edge From="makearray28.Array" To="Prerequisites" />
				</HasteTrigger>
				<HasteTrigger Name="90_gotoTestForge" PositionY="-1180" PositionX="-20">
					<Edge From="makearray13.Array" To="ConsoleCommands" />
				</HasteTrigger>
				<HasteTrigger Name="99_pseudoHibernateBlacksmithing" PositionY="-310" PositionX="-1260" />
				<activity_activation_hibernation_filter Name="hibernationprotector" PositionY="-840" PositionX="-1580" Namespace="legacy_of_the_forge">
					<Edge From="Counter" To="counter" />
					<Edge From="OnWake" To="onwake" />
				</activity_activation_hibernation_filter>
				<IfFunction Name="ifnot27" PositionY="-740" PositionX="-1130" MethodName="math::boolean::Not" DeclaringType="math::boolean">
					<Edge From="debug_aktivovan" To="Value" />
					<Edge From="hibernationprotector.onwakeonceperactivation" To="Exec" />
				</IfFunction>
				<kovaci_zakazka Name="kovaci_zakazka" PositionY="-920" PositionX="550" RequiredForOutput="kutnohorsko" />
				<MakeArray Name="makearray13" PositionY="-1150" PositionX="-370" TypeT="Strings">
					<Constant Name="A" Value="goto blacksmithing_testForge" />
				</MakeArray>
				<MakeArray Name="makearray26" PositionY="-1180" PositionX="-1480" TypeT="wh::conceptmodule::ConceptPaths">
					<Constant Name="A" Value="uchazec.endQuest" />
					<Constant Name="B" Value="pusko.stream" />
				</MakeArray>
				<MakeArray Name="makearray28" PositionY="-1440" PositionX="-470" TypeT="wh::conceptmodule::ConceptPaths">
					<Constant Name="A" Value="01_rpg.unlock_blacksmithing_all" />
				</MakeArray>
				<Output Name="Output">
					<Edge From="zbrojnice.nastreamovat_truhlu" To="nastreamovat_truhlu_ve_zbrojnici" />
					<Edge From="prodejce_receptu.horst_dava_jindrovi_zlomeny_excalibur" To="horst_dava_jindrovi_zlomeny_excalibur">
						<Vertex>JmARtfo5</Vertex>
					</Edge>
					<Edge From="prodejce_receptu.jindra_kove_excalibur" To="jindra_kove_excalibur">
						<Vertex>e5wDRIVT</Vertex>
					</Edge>
					<Edge From="prodejce_receptu.horst_dava_jindrovi_zlomeny_durendal" To="horst_dava_jindrovi_zlomeny_durendal">
						<Vertex>4n9ABr0D</Vertex>
					</Edge>
					<Edge From="prodejce_receptu.jindra_kove_durendal" To="jindra_kove_durendal">
						<Vertex>q2oYgy1u</Vertex>
					</Edge>
					<Edge From="prodejce_receptu.horst_dava_jindrovi_zlomeny_mec_4_evangelistu" To="horst_dava_jindrovi_zlomeny_mec_4_evangelistu">
						<Vertex>ult6mk7k</Vertex>
					</Edge>
					<Edge From="prodejce_receptu.jindra_kove_4_evangelisty" To="jindra_kove_4_evangelisty">
						<Vertex>PfgRIH5u</Vertex>
					</Edge>
					<Edge From="prodejce_receptu.fail_aktivity_prodejce_receptu" To="fail_aktivity_prodejce_receptu">
						<Vertex>bImKIY4d</Vertex>
					</Edge>
					<Edge From="prodejce_receptu.quest_progress_none" To="prodejce_receptu_1__quest_progress_none">
						<Vertex>qDTFaLsk</Vertex>
					</Edge>
					<Edge From="zubar.quest_progress_none" To="zubar__quest_progress_none" />
					<Edge From="zbrojnice.jindra_odevzdava_klic" To="jindra_predal_klic_strazi" />
					<Edge From="zbrojnice.aktivita_konci_neuspesne" To="konci_quest">
						<Vertex>UnTXuneC</Vertex>
					</Edge>
					<Edge From="zbrojnice.aktivita_konci_uspesne" To="konci_quest">
						<Vertex>UnTXuneC</Vertex>
					</Edge>
					<Edge From="zbrojnice.jindra_dostava_info_o_klici" To="jindra_se_dozvida_o_klici_ve_meste" />
					<Edge From="zbrojnice.jindra_nachazi_klic" To="zbrojnice__jindra_sebral_klic" />
					<Edge From="ucednik.aktivita_zacala" To="aktivita_zacala" />
					<Edge From="zubar.zubar__nastavit_pacientovi_zakrvacenou_hlavu" To="zubar__nastavit_pacientovi_zakrvacenou_hlavu" />
					<Edge From="zubar.first_objective_none" To="zubar__first_objective_none" />
					<Edge From="zubar.zubar__pacient_svevolne_pada_do_bezvedomi" To="zubar__pacient_svevolne_pada_do_bezvedomi" />
					<Edge From="prodejce_receptu.prodejce_receptu__nastreamovat" To="prodejce_receptu__nastreamovat">
						<Vertex>bkala1zX</Vertex>
					</Edge>
					<Edge From="prodejce_receptu.prodejce_receptu__odejit_z_levelu" To="prodejce_receptu__odejit_z_levelu">
						<Vertex>SUr9AlEG</Vertex>
					</Edge>
					<Edge From="prodejce_receptu.jindra_ma_za_ukol_vykovat_draci_sekeru" To="jindra_ma_za_ukol_vykovat_draci_sekeru">
						<Vertex>cvcuKmUR</Vertex>
					</Edge>
				</Output>
				<prodejce_receptu Name="prodejce_receptu" PositionY="670" PositionX="510" RequiredForOutput="kutnohorsko">
					<Edge From="vybirani_typu_aktivity.vybran_prodejce_receptu_1" To="vybran_prodejce_receptu_1">
						<Vertex>XssunGaU</Vertex>
					</Edge>
					<Edge From="OnHibernate" To="zruseni_nevybranych_aktivit">
						<Vertex>qYqSwIRI</Vertex>
						<Vertex>RCjTBSRz</Vertex>
						<Vertex>V4tH1hVl</Vertex>
					</Edge>
					<Edge From="vybirani_typu_aktivity.vybran_prodejce_receptu_2" To="vybran_prodejce_receptu_1">
						<Vertex>XssunGaU</Vertex>
					</Edge>
					<Edge From="vybirani_typu_aktivity.vybran_prodejce_receptu_3" To="vybran_prodejce_receptu_1">
						<Vertex>XssunGaU</Vertex>
					</Edge>
					<Edge From="99_pseudoHibernateBlacksmithing.OnTrigger" To="zruseni_nevybranych_aktivit">
						<Vertex>RCjTBSRz</Vertex>
						<Vertex>V4tH1hVl</Vertex>
					</Edge>
					<Edge From="vybirani_typu_aktivity.vybran_prodejce_receptu_4" To="vybran_prodejce_receptu_1">
						<Vertex>XssunGaU</Vertex>
					</Edge>
					<Edge From="jindra_vi_o_drakovi" To="jindra_vi_o_drakovi">
						<Vertex>Lrhkn5XL</Vertex>
					</Edge>
					<Edge From="drak_state" To="drak_state">
						<Vertex>bIEBBjTA</Vertex>
					</Edge>
					<Edge From="jindra_ziskal_fejxcalibur" To="jindra_ziskal_fejxcalibur">
						<Vertex>IlTuGyut</Vertex>
					</Edge>
					<Edge From="jindra_ziskal_durensral" To="jindra_ziskal_durensral">
						<Vertex>yEUUVed8</Vertex>
					</Edge>
					<Edge From="jindra_ziskal_mec_4_evangelistu" To="jindra_ziskal_mec_4_evangelistu">
						<Vertex>LwDPwy4f</Vertex>
					</Edge>
					<Edge From="jindra_ziskal_draci_zbran" To="jindra_ziskal_draci_zbran">
						<Vertex>E4PcoHP3</Vertex>
					</Edge>
				</prodejce_receptu>
				<ucednik Name="ucednik" PositionY="-140" PositionX="530" RequiredForOutput="kutnohorsko">
					<Edge From="vybirani_typu_aktivity.vybrana_unikatni_aktivita" To="zobrazit_dostupnou_aktivitu" />
					<Edge From="vybirani_typu_aktivity.vybran_ucednik_2" To="ucednik_2__zobrazit_dostupnou_aktivitu" />
					<Edge From="OnHibernate" To="zruseni_nevybranych_aktivit">
						<Vertex>qYqSwIRI</Vertex>
						<Vertex>RCjTBSRz</Vertex>
						<Vertex>V4tH1hVl</Vertex>
					</Edge>
					<Edge From="99_pseudoHibernateBlacksmithing.OnTrigger" To="zruseni_nevybranych_aktivit">
						<Vertex>RCjTBSRz</Vertex>
						<Vertex>V4tH1hVl</Vertex>
					</Edge>
				</ucednik>
				<vybirani_typu_aktivity Name="vybirani_typu_aktivity" PositionY="-870" PositionX="-750">
					<Edge From="zubar.muze_byt_nabrana" To="muze_byt_nabrana_2">
						<Vertex>zGvNtH0h</Vertex>
						<Vertex>tAFe39rF</Vertex>
					</Edge>
					<Edge From="01_initBlacksmithing.OnTrigger" To="vybrano_kovani">
						<Vertex>hakRvldU</Vertex>
					</Edge>
					<Edge From="zbrojnice.muze_byt_nabrana" To="aktivita_zbrojnice_muze_byt_nabrana">
						<Vertex>z5fYoFNe</Vertex>
						<Vertex>uBbaqB2v</Vertex>
					</Edge>
					<Edge From="ifnot27.True" To="vybrano_kovani">
						<Vertex>hakRvldU</Vertex>
					</Edge>
					<Edge From="prodejce_receptu.aktivita_prodejce_receptu_1_muze_byt_nabrana" To="aktivita_prodejce_receptu_muze_byt_nabrana">
						<Vertex>GCN70m86</Vertex>
						<Vertex>JknQCySb</Vertex>
					</Edge>
					<Edge From="prodejce_receptu.aktivita_prodejce_receptu_2_muze_byt_nabrana" To="aktivita_prodejce_receptu_2_muze_byt_nabrana">
						<Vertex>CgxULrM5</Vertex>
						<Vertex>52hPP16C</Vertex>
					</Edge>
					<Edge From="prodejce_receptu.aktivita_prodejce_receptu_3_muze_byt_nabrana" To="aktivita_prodejce_receptu_3_muze_byt_nabrana">
						<Vertex>k1VkjTW1</Vertex>
						<Vertex>VelBVcsC</Vertex>
					</Edge>
					<Edge From="prodejce_receptu.aktivita_prodejce_receptu_4_muze_byt_nabrana" To="aktivita_prodejce_receptu_4_muze_byt_nabrana">
						<Vertex>vqXBmy7b</Vertex>
						<Vertex>x4tyIsto</Vertex>
					</Edge>
					<Edge From="ucednik.muze_byt_nabrana_3" To="muze_byt_nabrana_3">
						<Vertex>X8YhcruX</Vertex>
						<Vertex>vHajkV4a</Vertex>
					</Edge>
					<Edge From="ucednik.aktivita_ucednik_2_muze_byt_nabrana" To="aktivita_ucednik_2_muze_byt_nabrana">
						<Vertex>jDzvfXYd</Vertex>
						<Vertex>7WSIVQNr</Vertex>
					</Edge>
				</vybirani_typu_aktivity>
				<zbrojnice Name="zbrojnice" PositionY="170" PositionX="510" RequiredForOutput="kutnohorsko">
					<Edge From="vybirani_typu_aktivity.vybrana_zbrojirna" To="zobrazit_dostupnou_aktivitu" />
					<Edge From="OnHibernate" To="zruseni_nevybranych_aktivit">
						<Vertex>qYqSwIRI</Vertex>
						<Vertex>RCjTBSRz</Vertex>
						<Vertex>V4tH1hVl</Vertex>
					</Edge>
					<Edge From="99_pseudoHibernateBlacksmithing.OnTrigger" To="zruseni_nevybranych_aktivit">
						<Vertex>RCjTBSRz</Vertex>
						<Vertex>V4tH1hVl</Vertex>
					</Edge>
				</zbrojnice>
				<zubar Name="zubar" PositionY="-460" PositionX="520" RequiredForOutput="kutnohorsko">
					<Edge From="vybirani_typu_aktivity.vybran_zubar" To="zobrazit_dostupnou_aktivitu" />
					<Edge From="OnHibernate" To="zruseni_nevybranych_aktivit">
						<Vertex>qYqSwIRI</Vertex>
						<Vertex>RCjTBSRz</Vertex>
						<Vertex>V4tH1hVl</Vertex>
					</Edge>
					<Edge From="99_pseudoHibernateBlacksmithing.OnTrigger" To="zruseni_nevybranych_aktivit">
						<Vertex>RCjTBSRz</Vertex>
						<Vertex>V4tH1hVl</Vertex>
					</Edge>
					<Edge From="jindra_trhal_zub_v_poi_na_kovarne" To="jindra_trhal_zub_v_poi_na_kovarne">
						<Vertex>YYmI9kMz</Vertex>
						<Vertex>ThYEKtIQ</Vertex>
					</Edge>
				</zubar>
			</Nodes>
			<EdgeVertices>
				<EdgeVertex Name="4n9ABr0D" PositionY="1100" PositionX="2430" />
				<EdgeVertex Name="52hPP16C" PositionY="1730" PositionX="-530" />
				<EdgeVertex Name="7WSIVQNr" PositionY="1610" PositionX="-530" />
				<EdgeVertex Name="bIEBBjTA" PositionY="790" PositionX="-1430" />
				<EdgeVertex Name="bImKIY4d" PositionY="1280" PositionX="2430" />
				<EdgeVertex Name="bkala1zX" PositionY="1370" PositionX="2430" />
				<EdgeVertex Name="CgxULrM5" PositionY="1730" PositionX="760" />
				<EdgeVertex Name="cvcuKmUR" PositionY="1310" PositionX="2430" />
				<EdgeVertex Name="E4PcoHP3" PositionY="870" PositionX="-1430" />
				<EdgeVertex Name="e5wDRIVT" PositionY="1040" PositionX="2430" />
				<EdgeVertex Name="GCN70m86" PositionY="1700" PositionX="760" />
				<EdgeVertex Name="hakRvldU" PositionY="-840" PositionX="-850" />
				<EdgeVertex Name="IlTuGyut" PositionY="810" PositionX="-1430" />
				<EdgeVertex Name="jDzvfXYd" PositionY="1610" PositionX="760" />
				<EdgeVertex Name="JknQCySb" PositionY="1700" PositionX="-530" />
				<EdgeVertex Name="JmARtfo5" PositionY="1010" PositionX="2430" />
				<EdgeVertex Name="k1VkjTW1" PositionY="1760" PositionX="760" />
				<EdgeVertex Name="Lrhkn5XL" PositionY="770" PositionX="-1430" />
				<EdgeVertex Name="LwDPwy4f" PositionY="850" PositionX="-1430" />
				<EdgeVertex Name="PfgRIH5u" PositionY="1220" PositionX="2430" />
				<EdgeVertex Name="q2oYgy1u" PositionY="1130" PositionX="2430" />
				<EdgeVertex Name="qDTFaLsk" PositionY="1340" PositionX="2430" />
				<EdgeVertex Name="qYqSwIRI" PositionY="-50" PositionX="-1460" />
				<EdgeVertex Name="RCjTBSRz" PositionY="-50" PositionX="-900" />
				<EdgeVertex Name="SUr9AlEG" PositionY="1400" PositionX="2500" />
				<EdgeVertex Name="tAFe39rF" PositionY="1790" PositionX="-530" />
				<EdgeVertex Name="ThYEKtIQ" PositionY="-10" PositionX="280" />
				<EdgeVertex Name="uBbaqB2v" PositionY="1640" PositionX="-530" />
				<EdgeVertex Name="ult6mk7k" PositionY="1190" PositionX="2430" />
				<EdgeVertex Name="UnTXuneC" PositionY="580" PositionX="950" />
				<EdgeVertex Name="V4tH1hVl" PositionY="-50" PositionX="280" />
				<EdgeVertex Name="VelBVcsC" PositionY="1760" PositionX="-530" />
				<EdgeVertex Name="vHajkV4a" PositionY="1580" PositionX="-530" />
				<EdgeVertex Name="vqXBmy7b" PositionY="1670" PositionX="760" />
				<EdgeVertex Name="x4tyIsto" PositionY="1670" PositionX="-530" />
				<EdgeVertex Name="X8YhcruX" PositionY="1580" PositionX="760" />
				<EdgeVertex Name="XssunGaU" PositionY="-310" PositionX="-340" />
				<EdgeVertex Name="yEUUVed8" PositionY="830" PositionX="-1430" />
				<EdgeVertex Name="YYmI9kMz" PositionY="-10" PositionX="-1480" />
				<EdgeVertex Name="z5fYoFNe" PositionY="1640" PositionX="760" />
				<EdgeVertex Name="zGvNtH0h" PositionY="1790" PositionX="770" />
			</EdgeVertices>
			<Types>
				<Type TypeName="ProdejceReceptu_GettingRecipe">
					<StateTypeEnumeration Name="None" ObjectiveValueType="None" />
					<StateTypeEnumeration Name="UseRecipe" ObjectiveValueType="Started" />
					<StateTypeEnumeration Name="DroppedRecipe" ObjectiveValueType="Updated" />
					<StateTypeEnumeration Name="Done" ObjectiveValueType="Completed" />
					<StateTypeEnumeration Name="Aborted" ObjectiveValueType="None" />
				</Type>
				<Type TypeName="PasCudnosti_LockDifficulty">
					<StateTypeEnumeration Name="None" ObjectiveValueType="None" />
					<StateTypeEnumeration Name="VeryEasy" ObjectiveValueType="None" />
					<StateTypeEnumeration Name="Easy" ObjectiveValueType="None" />
					<StateTypeEnumeration Name="Normal" ObjectiveValueType="None" />
					<StateTypeEnumeration Name="Hard" ObjectiveValueType="None" />
					<StateTypeEnumeration Name="VeryHard" ObjectiveValueType="None" />
				</Type>
				<Type TypeName="LegacyOfTheForge_UcednikType">
					<StateTypeEnumeration Name="RegularSword" ObjectiveValueType="None" />
					<StateTypeEnumeration Name="DrunkAxe" ObjectiveValueType="None" />
				</Type>
			</Types>
			<Assets>
				<SoulAsset Name="randomNpcPool" />
				<SoulAsset Name="armorer" SharedSoulGuids="6099ee6d-1d4b-4340-bb0d-1c7b91313fcf" />
				<SoulAsset Name="gunsmith" SharedSoulGuids="f6aa4907-90fa-434c-85f7-d3bd96c326b6" />
				<SoulAsset Name="apprentice" SharedSoulGuids="198dce96-5d79-4da5-a5f0-049deab6bdb9" />
				<TagPointAsset Name="apprenticeSwitchDialogSource" />
				<DialogueHolderAsset Name="afterBlacksmithingDialogHolder" />
				<SmitheryAsset Name="henrysForge" />
				<SoulAsset Name="recipeSalesman" SharedSoulGuids="1837e841-1969-4df8-90d1-ff55eea7643c" />
				<TriggerAreaAsset Name="forgeArea" />
			</Assets>
			<Text StringName="aktivity_kovani_L6sD" Text="A201 Kování" />
			<Elements>
				<GameplayActionElement>
					<Text StringName="a201_kova_k_jindrichovi_d_CoCF" Text="K Jindřichovi do kovárny chodí různí lidé se zakázkami kování (tj. vykovej takovou a makovou sekeru), jenže se to zaplete do složitějšího příběhu." />
				</GameplayActionElement>
			</Elements>
		</ActivityType>
	</Skald>
</Database>